gamepadinfo.py
gamepadinfo-0.9.1.dist-info/DESCRIPTION.rst
gamepadinfo-0.9.1.dist-info/METADATA
gamepadinfo-0.9.1.dist-info/RECORD
gamepadinfo-0.9.1.dist-info/WHEEL
gamepadinfo-0.9.1.dist-info/entry_points.txt
gamepadinfo-0.9.1.dist-info/metadata.json
gamepadinfo-0.9.1.dist-info/top_level.txt
