Metadata-Version: 2.0
Name: gamepadinfo
Version: 0.9.1
Summary: Detect gamepads and show reads its state on Linux
Home-page: https://github.com/godfryd/gamepadinfo
Author: Michal Nowikowski
Author-email: godfryd@gmail.com
License: MIT
Keywords: gamepad gamecontroller joystick
Platform: UNKNOWN
Classifier: Development Status :: 4 - Beta
Classifier: Intended Audience :: Developers
Classifier: Topic :: Software Development :: Build Tools
Classifier: License :: OSI Approved :: MIT License
Classifier: Programming Language :: Python :: 3
Classifier: Programming Language :: Python :: 3.5
Requires-Dist: PySDL2
Requires-Dist: evdev
Requires-Dist: pyudev
Requires-Dist: urwid
